CHANGELOG.txt
CONTRIBUTORS.txt
Copying_ProjectX
INSTALL.rst
LICENSE.txt
MANIFEST.in
README.rst
ReadMe_ProjectX.txt
setup.py
bin/mkvenc
bin/mkvenc.cmd
bin/ts2mkv
bin/ts2mkv.cmd
ts2mkv/ProjectX.jar
ts2mkv/__init__.py
ts2mkv/audiopresets.ini
ts2mkv/checkenv.py
ts2mkv/colours.tbl
ts2mkv/common.py
ts2mkv/commonargparse.py
ts2mkv/demuxmkv.py
ts2mkv/demuxts.py
ts2mkv/encodetracks.py
ts2mkv/metadata.py
ts2mkv/mkvenc.ini
ts2mkv/mkvenc.py
ts2mkv/mkvinfo.py
ts2mkv/muxmkv.py
ts2mkv/paths_win.ini
ts2mkv/process.py
ts2mkv/srtadjust.py
ts2mkv/ts2mkv.ini
ts2mkv/ts2mkv.py
ts2mkv/tsdemux.ini
ts2mkv/tsinfo.py
ts2mkv/videopresets.ini
ts2mkv.egg-info/PKG-INFO
ts2mkv.egg-info/SOURCES.txt
ts2mkv.egg-info/dependency_links.txt
ts2mkv.egg-info/not-zip-safe
ts2mkv.egg-info/top_level.txt
ts2mkv/dll/RAWIO16.DLL
ts2mkv/dll/RAWIO32.dll
ts2mkv/dll/rawread.dll
ts2mkv/lib/LICENSE.txt
ts2mkv/lib/NOTICE.txt
ts2mkv/lib/commons-net-1.3.0.jar
ts2mkv/lib/idctref.dll
ts2mkv/lib/idctsse.dll
ts2mkv/lib/jakarta-oro-2.0.8.jar
ts2mkv/lib/OS2/build.cmd
ts2mkv/lib/OS2/idctsse.dll
ts2mkv/lib/c_src/idct_ref/build.bat
ts2mkv/lib/c_src/idct_ref/idctref.c
ts2mkv/lib/c_src/idct_ref/net_sourceforge_dvb_projectx_video_IDCTRefNative.c
ts2mkv/lib/c_src/idct_sse/IDCT_CLI.C
ts2mkv/lib/c_src/idct_sse/IDCT_CLI.H
ts2mkv/lib/c_src/idct_sse/IDCT_REF.C
ts2mkv/lib/c_src/idct_sse/IDCT_REF.H
ts2mkv/lib/c_src/idct_sse/build.bat
ts2mkv/lib/c_src/idct_sse/net_sourceforge_dvb_projectx_video_IDCTSseNative.c