Metadata-Version: 1.1
Name: ts2mkv
Version: 2.0.1
Summary: Converts DVB Transport Stream (.ts) files into Matroska (.mkv)
Home-page: https://bitbucket.org/ts2mkv/ts2mkv
Author: Jaakko Vuori
Author-email: jaakko.vuori@gmail.com
License: LICENSE.txt
Platform: UNKNOWN
Classifier: Programming Language :: Python
Classifier: Programming Language :: Python :: 2.7
Classifier: Environment :: Console
Classifier: Intended Audience :: End Users/Desktop
Classifier: License :: OSI Approved :: MIT License
Classifier: Operating System :: POSIX :: Linux
Classifier: Operating System :: Microsoft :: Windows
Classifier: Topic :: Multimedia :: Sound/Audio :: Conversion
